LICENSE
MANIFEST.in
README.md
setup.cfg
setup.py
pingmon/__init__.py
pingmon/getipgeo.py
pingmon/pinggraph.py
pingmon/pingmon.py
pingmon/pmonClass.py
pingmon.egg-info/PKG-INFO
pingmon.egg-info/SOURCES.txt
pingmon.egg-info/dependency_links.txt
pingmon.egg-info/entry_points.txt
pingmon.egg-info/not-zip-safe
pingmon.egg-info/requires.txt
pingmon.egg-info/top_level.txt